LICENSE
MANIFEST.in
README
setup.py
django_googleforms.egg-info/PKG-INFO
django_googleforms.egg-info/SOURCES.txt
django_googleforms.egg-info/dependency_links.txt
django_googleforms.egg-info/not-zip-safe
django_googleforms.egg-info/top_level.txt
googleforms/__init__.py
googleforms/forms/__init__.py
googleforms/models/__init__.py
googleforms/models/fields.py