Metadata-Version: 1.0
Name: django-googleforms
Version: 0.8
Summary: Application which help with parsing google forms.
Home-page: https://github.com/matllubos/django-googleforms
Author: Lubos Matl
Author-email: matllubos@gmail.com
License: GPL
Keywords: django,admin,pages,google forms
Platform: UNKNOWN
Classifier: Development Status :: 4 - Beta
Classifier: Environment :: Web Environment
Classifier: Framework :: Django
Classifier: Intended Audience :: Developers
Classifier: Intended Audience :: End Users/Desktop
Classifier: License :: OSI Approved :: GNU General Public License (GPL)
Classifier: Natural Language :: Czech
Classifier: Operating System :: OS Independent
Classifier: Programming Language :: Python
Classifier: Topic :: Internet :: WWW/HTTP :: Dynamic Content
Classifier: Topic :: Internet :: WWW/HTTP :: Site Management
